alu.v
`include "minicpu.h"
// 执行阶段**
// 生成访问数据内容RAM的地址和数据
// 根据ifun执行指令指明的操作，完成各种运算的操作
// 计算内存引用的有效地址； 增加或减少栈指针
// 计算得到valE
module ALU (
    input wire [`DataBus] A,
    input wire [`DataBus] B,  // E = A op B
    output reg [`DataBus] E,  
	input wire [3:0] op,
    output reg [1:0] cc  // Cond. code: set when E = A - B
);						 //    (A==B)? 1x: ((A>B)? 01: 00)
	always @(*) begin
		E = 8'hxx;
		cc = 2'bxx;
		case (op)
			4'h0 : E = A + B;
			4'h1 : begin
				E = A - B;
				cc = {!E, $signed(E)>0};
			end
			4'h3 : E = B + 1;
			4'h4 : E = B - 1;
			endcase
		end
endmodule

regfile.v
`include "minicpu.h"
// 译码和写回
// 译码阶段， 从寄存器文件中读入最多两个操作数
// 读入rA和rB指明的寄存器

module regfile (
	input wire [2:0] srcA,
	input wire [2:0] srcB,
	output reg [`DataBus] valA,
	output reg [`DataBus] valB,
	input wire [2:0] dstM,
	input wire [2:0] dstE,
	input wire [`DataBus] valM,
	input wire [`DataBus] valE,
	input wire clk,
	input wire we_	//写控制信号
);
	reg [`DataBus] rf [7:1]; // R0 is zero.
	
	// 译码阶段读取寄存器内容
	// 只要有输入就有输出
	// scrA如果有值的话 valA就来自寄存器文件，否则来自寄存器0
	always @(*) begin
		valA = (srcA)? rf[srcA]: 0;
		valB = (srcB)? rf[srcB]: 0;
		$write("%-5d: !!DecodePhase: \n", $time);
		$write("       !!valAFetching: regNum:%o  content:%x  result:valA=%x \n", srcA, rf[srcA], valA);
		$write("      !!valBFetching: regNum:%o  content:%x  result:valB=%x \n", srcB, rf[srcB], valB);
		end
		
	// 时钟上升 写入寄存器
	always @(posedge clk)
		if(we_==`ENABLE_) begin
			// 判断是将valM还是valE的值写回到寄存器当中
			// 跟指令类型有关
			if(dstM) begin 
				rf[dstM] <= valM;
				$write("%-5d: !!!!MemoryAccessResult: ",$time);	
				$write("       !!!!regNum:%o  ", dstM);
				$write("       !!!!valM: %x(x),%d(d) ", valM,valM);
				$write("\n");
			end
			if(dstE && dstE!=dstM) begin 
				rf[dstE] <= valE;
				$write("%-5d: !!!!ExecutionResult: ",$time);	
				$write("       !!!!regNum:%o  ", dstE);
				$write("       !!!!valE: %x(x),%d(d) ", valE,valE);
				$write("\n");
			end
		end
endmodule

pc.v
`include "minicpu.h"

// 更新下一条指令的地址
// 即更新PC的值
module PC (
	input wire [`AddrBus] new_pc,	// 更新后的PC
	output reg [`AddrBus] pc,		// 输出下一步要执行的指令地址
	input wire clk,
	input wire rst_
);
	always @ (posedge clk, negedge rst_)
		if (rst_==`ENABLE_) pc <= 0;
		else pc <= new_pc;
endmodule

minicpu.v
`include "minicpu.h"

`define ins	 rom_data[23:20]
`define fun	 rom_data[19:16]
`define rA	 rom_data[14:12]
`define rB	 rom_data[10: 8]
`define rC	 rom_data[ 6: 4]
`define valC rom_data[ 7: 0]

module minicpu (
	output wire [`AddrBus] ram_addr,
	output wire [`DataBus] ram_d_in,
	input  wire [`DataBus] ram_d_out,
	output reg ram_rd_, ram_wr_,

	output wire [`AddrBus] rom_addr,
	input  wire [`Rom_Bus] rom_data,

	input  wire clk,
	input  wire rst_
);
	reg  [`AddrBus] valP;
	wire [`DataBus] valA, valB, valE;
	reg  [2:0] dstM, dstE;
	reg  [`DataBus] aluB;
	reg  [`DataBus] aluA;
	reg  [2:0] regA;
	reg  [2:0] regB;
	reg  [3:0] op;	// operator
	wire [1:0] cc;	// condition
	reg  [`AddrBus] new_pc;	
	
	// 
	PC PC (
	.new_pc (new_pc),
	.pc     (rom_addr),
	.clk    (clk),
	.rst_   (rst_)
	);
	
	always @(*) begin
		valP = rom_addr + ((`ins==`HLT)? 0: (`ins==`NOP||`ins==`RET)? 1: 3);
		//
		dstM = (`ins==`POP)? `rA : (`ins==`LD )? `rB: `R0;
		// 运算类指令、传送指令
		dstE = (`ins==`PUSH||`ins==`POP||`ins==`CALL||`ins==`RET)? `RSP : (`ins==`OPR)? `rC: (`ins==`OPI||`ins==`IRMOV||`ins==`RRMOV)? `rB: `R0;
		end
	//regA = (`ins==`POP)? `RSP : `rA;
	//regB = (`ins==`PUSH||`ins==`POP)? `RSP : `rB;
	regfile regfile (
	.srcA ((`ins==`POP||`ins==`RET)? `RSP:`rA),
	.srcB ( (`ins==`PUSH||`ins==`POP||`ins==`CALL||`ins==`RET)? `RSP:`rB ),
	.valA (valA),
	.valB (valB),
	.dstM (dstM),
	.dstE (dstE),	
	.valM (ram_d_out),
	.valE (valE),
	.clk  (clk),
	.we_  (~rst_)
	);
	// 给执行阶段准备数据
	always @(*) begin
		aluB = (`ins==`RRMOV)? valA:(`ins==`LD||`ins==`ST||`ins==`OPI||{`ins, `fun}=={`JMP, `BNG}||`ins==`IRMOV||`ins==`RMMOV)? `valC: valB;
		op = (`ins==`POP||`ins==`RET)? 4'h4 : (`ins==`PUSH||`ins==`CALL)? 4'h3: (`ins==`IRMOV||`ins==`RMMOV||`ins==`RRMOV)? `ADD : (`ins==`OPR||`ins==`OPI)? `fun : (`ins==`JMP&&`fun!=`BNG)? `SUB: `ADD;
		end

		// 生成访问数据内容RAM的地址和数据
	//aluA = (`ins==`RMMOV) ? valB : valA;
	ALU ALU (
    .A  ((`ins==`RRMOV)? 8'h0: (`ins==`RMMOV) ? valB : valA),
    .B  (aluB),
    .E  (valE),
	.op (op),
    .cc (cc)	// set when E = A - B, (A==B)? 1x: (A>B)? 01: 00.
	);

	assign ram_addr = (`ins==`POP||`ins==`RET) ? valA : valE;	// 访存阶段所需的内存地址
	assign ram_d_in = (`ins==`CALL)? valP:(`ins==`RMMOV||`ins==`PUSH)? valA : valB;	// 访存阶段回写的数据
	// 访存阶段读写标志
	always @(*) begin
		ram_rd_ = (`ins==`LD||`ins==`POP||`ins==`RET)? `ENABLE_: `DISABLE_;
		ram_wr_ = (rst_&& (`ins==`ST||`ins==`PUSH||`ins==`RMMOV||`ins==`CALL))? `ENABLE_: `DISABLE_;
		end
		
	always @(*) begin
		new_pc = (`ins==`CALL)? `valC: (`ins==`RET)? ram_d_out:valP;	// 更新pc值
		if(`ins==`CALL) begin
			$write("----------!!CALL: %x\n",`valC);
		end
		if(`ins==`RET) begin
			$write("----------!!RET: %x\n",ram_d_out);
		end
		case ({`ins, `fun}) //无条件跳转
			{`JMP, `BNG} : new_pc = valE;
			{`JMP, `BEQ} : if( cc[1:1]) new_pc = `valC;
			{`JMP, `BNE} : if(~cc[1:1]) new_pc = `valC;
			{`JMP, `BLT} : if(~cc[1:1]&~cc[0:0]) new_pc = `valC;
			{`JMP, `BGT} : if(~cc[1:1]& cc[0:0]) new_pc = `valC;
			{`JMP, `BLE} : if( cc[1:1]|~cc[0:0]) new_pc = `valC;
			{`JMP, `BGE} : if( cc[1:1]| cc[0:0]) new_pc = `valC;
			endcase
		end
endmodule

rom.v
`include "minicpu.h"

module rom (
	input  wire [`AddrBus] addr,
	output wire [`Rom_Bus] data
);
	reg [`DataBus] mem [255:0];
	parameter BYTES = 256;
	
	// data是读出的指令 一次读出3个字节的指令编码
	assign data = {mem[addr], mem[addr+1], mem[addr+2]};

	initial
		//$readmemh("rom.txt", mem, 0, BYTES-1);
		$readmemh("testRom.txt", mem, 0, BYTES-1);
endmodule

ram.v
`include "minicpu.h"
// 访存阶段
// 读写操作：写数据、读数据
// ram中存放以0结尾的字符串
module ram (
	input wire [`AddrBus] addr,
	output reg [`DataBus] d_out,
	input wire [`DataBus] d_in,
	input wire rd_, 
	input wire wr_,
	input wire clk
);
	reg [`DataBus] mem [255:0];
	parameter BYTES = 256;
	integer j;
	// 读数据
	always @(*)
		if(rd_==`ENABLE_) begin 
			d_out = mem[addr];
			$write("!%-5d: !READ_: ", $time);	
			$write("%x", addr);
			$write("   ");
			$write("%x", d_out);
			$write("\n");	
		end
		else d_out = 8'hxx;
	// 写数据
	always @(posedge clk)
		if(wr_==`ENABLE_) begin 
			mem[addr] <= d_in;
			$write("!%-5d: !WRITE_: ", $time);	
			$write("%x", addr);
			$write("   ");
			$write("%x", d_in);
			$write("\n");	
			end
			
	
	integer i;											//
	initial												//
		$readmemh("ram.txt", mem, 0, BYTES-1);			//
	always @(negedge clk) begin							//
		$write("%3d: ", $time);							//
		for(i=0;i<48;i=i+1)								//
			if(mem[i]!==8'hxx) $write(" %x ", mem[i]);	// 
			else $write(" . ");							//
		$write("\n");									//
	end	
			
	//
endmodule

test.v
`timescale 10ns/1ns

`include "minicpu.h"

module test;
	wire [`AddrBus] ram_addr;
	wire [`DataBus] ram_d_in;
	wire [`DataBus] ram_d_out;
	wire ram_rd_, ram_wr_;
	wire [`AddrBus] rom_addr;
	wire [`Rom_Bus] rom_data;
	reg clk, rst_;
	integer i;
	
	parameter CYCLE = 1.0;
	
	// 访存，获取数据、写入变更后的数据
	ram ram (
	.addr	(ram_addr),
	.d_out	(ram_d_out),
	.d_in	(ram_d_in),
	.rd_	(ram_rd_),
	.wr_	(ram_wr_),
	.clk	(clk)
	);
	// 获取指令，共3字节
	rom rom (
	.addr	(rom_addr),
	.data	(rom_data)
	);
	
	minicpu minicpu (
	.ram_addr	(ram_addr),
	.ram_d_in	(ram_d_in),
	.ram_d_out	(ram_d_out),
	.ram_rd_	(ram_rd_),
	.ram_wr_	(ram_wr_),
	.rom_addr	(rom_addr),
	.rom_data	(rom_data),
	.clk		(clk),
	.rst_		(rst_)
	);

	// //
	always #(CYCLE/2) clk <= ~clk;
	
	// clock initial
	initial begin
		clk = 1'b1;
		rst_ = `ENABLE_;

	#(CYCLE+CYCLE/2)
		rst_ = `DISABLE_;
	end
	// // ？
	
	always @(negedge clk)
		if(rst_&&rom_data[23:20]==4'hf) #(CYCLE+0.1) begin 
			$write("%-5d, !!!!!!Program done!!!\n", $time);
			$finish;
		end
	
	initial begin
		$dumpfile("test.vcd");
		$dumpvars(0, rom);
		$dumpvars(0, ram);
		$dumpvars(0, minicpu);
		end
endmodule

test.vcd
$date
	Sat Jun 18 14:12:05 2022
$end
$version
	Icarus Verilog
$end
$timescale
	1ns
$end
$scope module test $end
$scope module rom $end
$var wire 8 ! addr [7:0] $end
$var wire 24 " data [23:0] $end
$upscope $end
$upscope $end
$scope module test $end
$scope module ram $end
$var wire 8 # addr [7:0] $end
$var wire 1 $ clk $end
$var wire 8 % d_in [7:0] $end
$var wire 1 & rd_ $end
$var wire 1 ' wr_ $end
$var reg 8 ( d_out [7:0] $end
$var integer 32 ) i [31:0] $end
$upscope $end
$upscope $end
$scope module test $end
$scope module minicpu $end
$var wire 1 $ clk $end
$var wire 1 * rst_ $end
$var wire 8 + valE [7:0] $end
$var wire 8 , valB [7:0] $end
$var wire 8 - valA [7:0] $end
$var wire 24 . rom_data [23:0] $end
$var wire 8 / rom_addr [7:0] $end
$var wire 8 0 ram_d_out [7:0] $end
$var wire 8 1 ram_d_in [7:0] $end
$var wire 8 2 ram_addr [7:0] $end
$var wire 2 3 cc [1:0] $end
$var reg 8 4 aluB [7:0] $end
$var reg 3 5 dstE [2:0] $end
$var reg 3 6 dstM [2:0] $end
$var reg 8 7 new_pc [7:0] $end
$var reg 4 8 op [3:0] $end
$var reg 1 & ram_rd_ $end
$var reg 1 ' ram_wr_ $end
$var reg 8 9 valP [7:0] $end
$scope module ALU $end
$var wire 8 : A [7:0] $end
$var wire 8 ; B [7:0] $end
$var wire 4 < op [3:0] $end
$var reg 8 = E [7:0] $end
$var reg 2 > cc [1:0] $end
$upscope $end
$scope module PC $end
$var wire 1 $ clk $end
$var wire 8 ? new_pc [7:0] $end
$var wire 1 * rst_ $end
$var reg 8 @ pc [7:0] $end
$upscope $end
$scope module regfile $end
$var wire 1 $ clk $end
$var wire 3 A dstE [2:0] $end
$var wire 3 B dstM [2:0] $end
$var wire 3 C srcA [2:0] $end
$var wire 3 D srcB [2:0] $end
$var wire 8 E valE [7:0] $end
$var wire 1 F we_ $end
$var wire 8 G valM [7:0] $end
$var reg 8 H valA [7:0] $end
$var reg 8 I valB [7:0] $end
$upscope $end
$upscope $end
$upscope $end
$enddefinitions $end
#0
$dumpvars
bx I
b0 H
bx G
1F
b1100100 E
b10 D
b0 C
b0 B
b10 A
b0 @
b11 ?
bx >
b1100100 =
b0 <
b1100100 ;
b0 :
b11 9
b0 8
b11 7
b0 6
b10 5
b1100100 4
bx 3
b1100100 2
bx 1
bx 0
b0 /
b11000000000001001100100 .
b0 -
bx ,
b1100100 +
0*
bx )
bx (
1'
1&
bx %
1$
b1100100 #
b11000000000001001100100 "
b0 !
$end
#5
b110000 )
0$
#10
1$
#15
b110000 )
0$
0F
1*
#20
b10000 #
b10000 2
bx %
bx 1
b11 D
b10000 +
b10000 =
b10000 E
b110 7
b110 ?
b10000 4
b10000 ;
b11 5
b11 A
b110 9
bx ,
bx I
b11000000000001100010000 "
b11000000000001100010000 .
b11 !
b11 /
b11 @
1$
#25
b110000 )
0$
#30
b1100100 :
b1100100 -
b1100100 H
b1010100 #
b1010100 2
b10000 %
b10000 1
b10 C
b1 3
b1 >
b1010100 +
b1010100 =
b1010100 E
b1001 7
b1001 ?
b1 8
b1 <
b1001 9
b10000 ,
b10000 I
b1100010010001100110000 "
b1100010010001100110000 .
b110 !
b110 /
b110 @
1$
#35
b110000 )
0$
#40
b1010100 -
b1010100 H
b1010100 #
b1010100 2
bx %
bx 1
b0 :
b101 D
b11 C
bx 3
bx >
b1010100 +
b1010100 =
b1010100 E
b1100 7
b1100 ?
b0 8
b0 <
b1010100 4
b1010100 ;
b101 5
b101 A
b1100 9
bx ,
bx I
b11100000011010100000000 "
b11100000011010100000000 .
b1001 !
b1001 /
b1001 @
1$
#45
b110000 )
0$
#50
b0 -
b0 H
b10100 #
b10100 2
bx %
bx 1
b0 :
b111 D
b0 C
b10100 +
b10100 =
b10100 E
b1111 7
b1111 ?
b10100 4
b10100 ;
b111 5
b111 A
b1111 9
bx ,
bx I
b11000000000011100010100 "
b11000000000011100010100 .
b1100 !
b1100 /
b1100 @
1$
#55
b110000 )
0$
#60
b10100 :
b10100 4
b10100 ;
b10100 -
b10100 H
b10100 #
b10100 2
b10100 %
b10100 1
b111 D
b111 C
b0 (
b0 0
b0 G
b10011 +
b10011 =
b10011 E
b10010 7
b10010 ?
0&
b100 8
b100 <
b100 6
b100 B
b10010 9
b10100 ,
b10100 I
b101100000100000000000000 "
b101100000100000000000000 .
b1111 !
b1111 /
b1111 @
1$
#65
b110000 )
0$
#70
b11 C
b1010100 %
b1010100 1
b1010100 :
bx (
bx 0
bx G
b10100 +
b10100 =
b10100 E
b10100 #
b10100 2
b10101 7
b10101 ?
0'
1&
b11 8
b11 <
b10011 4
b10011 ;
b0 6
b0 B
b10101 9
b10011 ,
b10011 I
b1010100 -
b1010100 H
b101000000011000000000000 "
b101000000011000000000000 .
b10010 !
b10010 /
b10010 @
1$
#75
b110000 )
0$
#80
b10100 :
b10101 #
b10101 2
b101 C
b10101 +
b10101 =
b10101 E
b11000 7
b11000 ?
b0 8
b0 <
b1 4
b1 ;
b0 5
b0 A
b11000 9
b10100 ,
b10100 I
b100000000101011100000001 "
b100000000101011100000001 .
b10101 !
b10101 /
b10101 @
1$
#85
b110000 )
0$
#90
b10101 #
b10101 2
b1010100 :
b10100 ,
b10100 I
b111 D
b10101 +
b10101 =
b10101 E
b11011 7
b11011 ?
b11 8
b11 <
b10100 4
b10100 ;
b111 5
b111 A
b11011 9
b101000000101000000000000 "
b101000000101000000000000 .
b11000 !
b11000 /
b11000 @
1$
#95
b110000 )
0$
#100
b0 :
b0 -
b0 H
b10110 #
b10110 2
b11110 %
b11110 1
b0 C
b10110 +
b10110 =
b10110 E
b11111 7
b11111 ?
b10101 4
b10101 ;
b11110 9
b10101 ,
b10101 I
b110000000000000000011111 "
b110000000000000000011111 .
b11011 !
b11011 /
b11011 @
1$
#105
b110000 )
0$
#110
b10110 :
b10110 -
b10110 H
b10110 #
b10110 2
b111 C
b11110 (
b11110 0
b11110 G
b10101 +
b10101 =
b10101 E
b10110 %
b10110 1
b11110 7
b11110 ?
1'
0&
b100 8
b100 <
b10110 4
b10110 ;
b100000 9
b10110 ,
b10110 I
b11010000xxxxxxxxxxxxxxxx "
b11010000xxxxxxxxxxxxxxxx .
b11111 !
b11111 /
b11111 @
1$
#115
b110000 )
0$
#120
b0 D
b101 C
b0 %
b0 1
b1010100 :
bx (
bx 0
bx G
b1010100 +
b1010100 =
b1010100 E
b1010100 #
b1010100 2
1&
b0 8
b0 <
b0 4
b0 ;
b0 5
b0 A
b11110 9
b0 ,
b0 I
b1010100 -
b1010100 H
b1111000011010000xxxxxxxx "
b1111000011010000xxxxxxxx .
b11110 !
b11110 /
b11110 @
1$
#125
b110000 )
0$
#130
1$
#135
b110000 )
0$
